{
	"class" : {
		"named:" : "PeterUhnak 3/4/2016 17:27:14" },
	"instance" : {
		"add:" : "PeterUhnak 3/4/2016 17:27:14",
		"addAll:" : "PeterUhnak 3/4/2016 17:27:14",
		"addedTo:" : "PeterUhnak 3/4/2016 17:27:14",
		"belongsTo" : "PeterUhnak 3/4/2016 17:27:14",
		"dcID" : "PeterUhnak 3/4/2016 17:27:14",
		"dcID:" : "PeterUhnak 3/4/2016 17:27:14",
		"detach" : "PeterUhnak 3/4/2016 17:27:14",
		"elements" : "PeterUhnak 3/4/2016 17:27:14",
		"has:" : "PeterUhnak 3/4/2016 17:27:14",
		"initialize" : "PeterUhnak 3/4/2016 17:27:14",
		"isInsideOf:" : "PeterUhnak 3/4/2016 17:27:14",
		"name" : "PeterUhnak 3/4/2016 17:27:14",
		"name:" : "PeterUhnak 3/4/2016 17:27:14",
		"ownedElements" : "PeterUhnak 3/4/2016 17:27:14",
		"owner" : "PeterUhnak 3/4/2016 17:27:14",
		"printOn:" : "PeterUhnak 3/4/2016 17:27:14",
		"relatedElements" : "PeterUhnak 3/4/2016 17:27:14",
		"remove" : "PeterUhnak 3/4/2016 17:27:14",
		"remove:" : "PeterUhnak 3/7/2016 17:32",
		"removeAll" : "PeterUhnak 3/4/2016 17:27:14",
		"removeFrom:" : "PeterUhnak 3/4/2016 17:27:14",
		"removeOwnedElements" : "PeterUhnak 3/4/2016 17:27:14",
		"removeRelatedElements" : "PeterUhnak 3/4/2016 17:27:14",
		"removedFrom:" : "PeterUhnak 3/4/2016 17:27:14",
		"removedFrom:do:" : "PeterUhnak 3/4/2016 17:27:14",
		"stonOn:" : "PeterUhnak 3/4/2016 17:27:14" } }
